GailBotTools/__init__.py
GailBotTools/configs/__init__.py
GailBotTools/configs/configData.toml
GailBotTools/configs/configs.py
GailBotTools/docker/__init__.py
GailBotTools/docker/client.py
GailBotTools/docker/utils.py
GailBotTools/plugin_structures/__init__.py
GailBotTools/plugin_structures/data_objects.py
GailBotTools/plugin_structures/general.py
GailBotTools/plugin_structures/marker_utterance_dict.py
GailBotTools/plugin_structures/methods.py
GailBotTools/plugin_structures/plugin.py
GailBotTools/plugin_structures/structure_interact.py
GailBotTools/plugin_structures/format/__init__.py
GailBotTools/plugin_structures/format/ca.py
GailBotTools/plugin_structures/format/chat.py
GailBotTools/plugin_structures/format/conversation_map.py
GailBotTools/plugin_structures/format/conversation_model.py
GailBotTools/plugin_structures/format/csv.py
GailBotTools/plugin_structures/format/nodes.py
GailBotTools/plugin_structures/format/speaker_map.py
GailBotTools/plugin_structures/format/text.py
GailBotTools/plugin_structures/format/utterance_map.py
GailBotTools/plugin_structures/format/word_tree.py
GailBotTools/plugin_structures/format/xml.py
GailBotTools-0.2.1.dist-info/LICENSE
GailBotTools-0.2.1.dist-info/METADATA
GailBotTools-0.2.1.dist-info/WHEEL
GailBotTools-0.2.1.dist-info/top_level.txt
GailBotTools-0.2.1.dist-info/RECORD
