Metadata-Version: 2.1
Name: GailBotTools
Version: 0.2.1
Summary: A set of tools for handling data to create GailBot plugins
Author-email: HiLab <hil@elist.tufts.edu>
License: MIT License
Project-URL: homepage, https://github.com/GailBot-System/GailBotPlugins
Keywords: gailbot,plugins,data,tools
Classifier: Programming Language :: Python :: 3
Classifier: License :: OSI Approved :: MIT License
Classifier: Operating System :: OS Independent
Requires-Python: >=3.6
License-File: LICENSE
Requires-Dist: lxml
Requires-Dist: toml
Requires-Dist: PyYAML
Requires-Dist: psutil
Requires-Dist: six
Requires-Dist: dict-to-dataclass
Provides-Extra: whisperx
Requires-Dist: whisperx; extra == "whisperx"
